{"channel":"axn","2026-04-26":[{"show":"Criminal Minds","category":"Temporada 1 Episodio 8 - Asesino nato","logo":"https://cdn.programaciontv.com.mx/wp-content/uploads/downloaded-images/axn/criminal-minds.webp","start":"22:40","end":"23:35"},{"show":"Criminal Minds","category":"Temporada 1 Episodio 9 - Descarrilado","logo":"https://cdn.programaciontv.com.mx/wp-content/uploads/downloaded-images/axn/criminal-minds-1.webp","start":"23:35","end":"00:30"}],"2026-04-27":[{"show":"Hawaii-Five-O","category":"Temporada 6 Episodio 1 - No agites el agua que está calma","logo":"https://cdn.programaciontv.com.mx/wp-content/uploads/downloaded-images/axn/hawaii-five-o.webp","start":"00:30","end":"01:25"},{"show":"CSI: Miami","category":"Temporada 1 Episodio 8 - Matadero","logo":"https://cdn.programaciontv.com.mx/wp-content/uploads/downloaded-images/axn/csi-miami.webp","start":"01:25","end":"02:20"},{"show":"CSI","category":"Temporada 6 Episodio 14 - Asesino","logo":"https://cdn.programaciontv.com.mx/wp-content/uploads/downloaded-images/axn/csi.webp","start":"02:20","end":"03:15"},{"show":"CSI","category":"Temporada 6 Episodio 15 - Piratas del tercer Reich","logo":"https://cdn.programaciontv.com.mx/wp-content/uploads/downloaded-images/axn/csi-1.webp","start":"03:15","end":"04:10"},{"show":"CSI","category":"Temporada 6 Episodio 16 - Reducido a humo","logo":"https://cdn.programaciontv.com.mx/wp-content/uploads/downloaded-images/axn/csi-2.webp","start":"04:10","end":"05:05"},{"show":"CSI","category":"Temporada 6 Episodio 17 - Me gusta mirar","logo":"https://cdn.programaciontv.com.mx/wp-content/uploads/downloaded-images/axn/csi-3.webp","start":"05:05","end":"06:00"},{"show":"CSI","category":"Temporada 6 Episodio 14 - Asesino","logo":"https://cdn.programaciontv.com.mx/wp-content/uploads/downloaded-images/axn/csi.webp","start":"06:00","end":"06:50"},{"show":"CSI","category":"Temporada 6 Episodio 15 - Piratas del tercer Reich","logo":"https://cdn.programaciontv.com.mx/wp-content/uploads/downloaded-images/axn/csi-1.webp","start":"06:50","end":"07:40"},{"show":"CSI","category":"Temporada 6 Episodio 16 - Reducido a humo","logo":"https://cdn.programaciontv.com.mx/wp-content/uploads/downloaded-images/axn/csi-2.webp","start":"07:40","end":"08:30"},{"show":"NCIS","category":"Temporada 21 Episodio 8 - Desalmado","logo":"https://cdn.programaciontv.com.mx/wp-content/uploads/downloaded-images/axn/ncis.webp","start":"08:30","end":"09:20"},{"show":"NCIS: Los Ángeles","category":"Temporada 12 Episodio 8 - El amor mata","logo":"https://cdn.programaciontv.com.mx/wp-content/uploads/downloaded-images/axn/ncis-los-ngeles.webp","start":"09:20","end":"10:10"},{"show":"Hawaii-Five-O","category":"Temporada 6 Episodio 3 - La aterradora tormenta está en la montaña","logo":"https://cdn.programaciontv.com.mx/wp-content/uploads/downloaded-images/axn/hawaii-five-o-1.webp","start":"10:10","end":"11:00"},{"show":"Hawaii-Five-O","category":"Temporada 6 Episodio 4 - Los planes mejor trazados","logo":"https://cdn.programaciontv.com.mx/wp-content/uploads/downloaded-images/axn/hawaii-five-o-2.webp","start":"11:00","end":"11:50"},{"show":"Criminal Minds","category":"Temporada 8 Episodio 5 - La buena tierra","logo":"https://cdn.programaciontv.com.mx/wp-content/uploads/downloaded-images/axn/criminal-minds-2.webp","start":"11:50","end":"12:40"},{"show":"Criminal Minds","category":"Temporada 8 Episodio 6 - El aprendizaje","logo":"https://cdn.programaciontv.com.mx/wp-content/uploads/downloaded-images/axn/criminal-minds-3.webp","start":"12:40","end":"13:30"},{"show":"Criminal Minds","category":"Temporada 8 Episodio 7 - Los caídos","logo":"https://cdn.programaciontv.com.mx/wp-content/uploads/downloaded-images/axn/criminal-minds-4.webp","start":"13:30","end":"14:20"},{"show":"CSI","category":"Temporada 1 Episodio 23 - El estrangulador del strip","logo":"https://cdn.programaciontv.com.mx/wp-content/uploads/downloaded-images/axn/csi-4.webp","start":"14:20","end":"15:10"},{"show":"CSI","category":"Temporada 2 Episodio 1 - Bravo, matón","logo":"https://cdn.programaciontv.com.mx/wp-content/uploads/downloaded-images/axn/csi-5.webp","start":"15:10","end":"16:00"},{"show":"CSI: Miami","category":"Temporada 1 Episodio 11 - Miedo en el campamento","logo":"https://cdn.programaciontv.com.mx/wp-content/uploads/downloaded-images/axn/csi-miami-1.webp","start":"16:00","end":"16:50"},{"show":"CSI: Miami","category":"Temporada 1 Episodio 12 - Orificio de entrada","logo":"https://cdn.programaciontv.com.mx/wp-content/uploads/downloaded-images/axn/csi-miami-2.webp","start":"16:50","end":"17:40"},{"show":"CSI: Miami","category":"Temporada 1 Episodio 13 - Desatino","logo":"https://cdn.programaciontv.com.mx/wp-content/uploads/downloaded-images/axn/csi-miami-3.webp","start":"17:40","end":"18:30"},{"show":"NCIS","category":"Temporada 21 Episodio 8 - Desalmado","logo":"https://cdn.programaciontv.com.mx/wp-content/uploads/downloaded-images/axn/ncis.webp","start":"18:30","end":"19:20"},{"show":"NCIS","category":"Temporada 21 Episodio 9 - El mejor corte","logo":"https://cdn.programaciontv.com.mx/wp-content/uploads/downloaded-images/axn/ncis-1.webp","start":"19:20","end":"20:10"},{"show":"NCIS","category":"Temporada 21 Episodio 10 - Locura en el arrecife","logo":"https://cdn.programaciontv.com.mx/wp-content/uploads/downloaded-images/axn/ncis-2.webp","start":"20:10","end":"21:00"},{"show":"Crimen en el trópico","category":"Temporada 5 Episodio 8 - Petite Anse","logo":"https://programaciontv.com.mx/wp-content/uploads/2026/01/pexels-caleboquendo-8254900.webp","start":"21:00","end":"22:00"},{"show":"Wild Cards","category":"Temporada 1 Episodio 8 - Eterno sol de la mente terapizada","logo":"https://programaciontv.com.mx/wp-content/uploads/2026/01/pexels-caleboquendo-8254900.webp","start":"22:00","end":"22:50"},{"show":"Wild Cards","category":"Temporada 1 Episodio 9 - Dentro del (con)hombre","logo":"https://programaciontv.com.mx/wp-content/uploads/2026/01/pexels-caleboquendo-8254900.webp","start":"22:50","end":"23:40"},{"show":"Criminal Minds","category":"Temporada 8 Episodio 5 - La buena tierra","logo":"https://cdn.programaciontv.com.mx/wp-content/uploads/downloaded-images/axn/criminal-minds-2.webp","start":"23:40","end":"00:30"}],"2026-04-28":[{"show":"Hawaii-Five-O","category":"Temporada 6 Episodio 3 - La aterradora tormenta está en la montaña","logo":"https://cdn.programaciontv.com.mx/wp-content/uploads/downloaded-images/axn/hawaii-five-o-1.webp","start":"00:30","end":"01:25"},{"show":"CSI: Miami","category":"Temporada 1 Episodio 11 - Miedo en el campamento","logo":"https://cdn.programaciontv.com.mx/wp-content/uploads/downloaded-images/axn/csi-miami-1.webp","start":"01:25","end":"02:20"},{"show":"CSI: NY","category":"Temporada 6 Episodio 3 - Latitud 40 grados","logo":"https://cdn.programaciontv.com.mx/wp-content/uploads/downloaded-images/axn/csi-ny.webp","start":"02:20","end":"03:15"},{"show":"CSI: NY","category":"Temporada 6 Episodio 4 - Muerte reconocida","logo":"https://cdn.programaciontv.com.mx/wp-content/uploads/downloaded-images/axn/csi-ny-1.webp","start":"03:15","end":"04:10"},{"show":"CSI: NY","category":"Temporada 6 Episodio 5 - Cicatrices de batalla","logo":"https://cdn.programaciontv.com.mx/wp-content/uploads/downloaded-images/axn/csi-ny-2.webp","start":"04:10","end":"05:05"},{"show":"CSI: NY","category":"Temporada 6 Episodio 6 - Me sucedió a mí","logo":"https://cdn.programaciontv.com.mx/wp-content/uploads/downloaded-images/axn/csi-ny-3.webp","start":"05:05","end":"06:00"},{"show":"CSI: NY","category":"Temporada 6 Episodio 3 - Latitud 40 grados","logo":"https://cdn.programaciontv.com.mx/wp-content/uploads/downloaded-images/axn/csi-ny.webp","start":"06:00","end":"06:50"},{"show":"CSI: NY","category":"Temporada 6 Episodio 4 - Muerte reconocida","logo":"https://cdn.programaciontv.com.mx/wp-content/uploads/downloaded-images/axn/csi-ny-1.webp","start":"06:50","end":"07:40"},{"show":"CSI: NY","category":"Temporada 6 Episodio 5 - Cicatrices de batalla","logo":"https://cdn.programaciontv.com.mx/wp-content/uploads/downloaded-images/axn/csi-ny-2.webp","start":"07:40","end":"08:30"},{"show":"NCIS","category":"Temporada 22 Episodio 1 - Nido vacío","logo":"https://cdn.programaciontv.com.mx/wp-content/uploads/downloaded-images/axn/ncis-3.webp","start":"08:30","end":"09:20"},{"show":"NCIS: Los Ángeles","category":"Temporada 12 Episodio 9 - Hecho consumado","logo":"https://cdn.programaciontv.com.mx/wp-content/uploads/downloaded-images/axn/ncis-los-ngeles-1.webp","start":"09:20","end":"10:10"},{"show":"Hawaii-Five-O","category":"Temporada 6 Episodio 5 - Gran mentira","logo":"https://cdn.programaciontv.com.mx/wp-content/uploads/downloaded-images/axn/hawaii-five-o-3.webp","start":"10:10","end":"11:00"},{"show":"Hawaii-Five-O","category":"Temporada 6 Episodio 6 - Monstruos","logo":"https://cdn.programaciontv.com.mx/wp-content/uploads/downloaded-images/axn/hawaii-five-o-4.webp","start":"11:00","end":"11:50"},{"show":"Criminal Minds","category":"Temporada 8 Episodio 8 - Las ruedas del autobús","logo":"https://cdn.programaciontv.com.mx/wp-content/uploads/downloaded-images/axn/criminal-minds-5.webp","start":"11:50","end":"12:40"},{"show":"Criminal Minds","category":"Temporada 8 Episodio 9 - Gloriosa luz","logo":"https://cdn.programaciontv.com.mx/wp-content/uploads/downloaded-images/axn/criminal-minds-6.webp","start":"12:40","end":"13:30"},{"show":"Criminal Minds","category":"Temporada 8 Episodio 10 - La lección","logo":"https://cdn.programaciontv.com.mx/wp-content/uploads/downloaded-images/axn/criminal-minds-7.webp","start":"13:30","end":"14:20"},{"show":"CSI","category":"Temporada 2 Episodio 2 - Asfixiado","logo":"https://cdn.programaciontv.com.mx/wp-content/uploads/downloaded-images/axn/csi-6.webp","start":"14:20","end":"15:10"},{"show":"CSI","category":"Temporada 2 Episodio 3 - Descompresión","logo":"https://cdn.programaciontv.com.mx/wp-content/uploads/downloaded-images/axn/csi-7.webp","start":"15:10","end":"16:00"},{"show":"CSI: Miami","category":"Temporada 1 Episodio 14 - Entrada forzada","logo":"https://cdn.programaciontv.com.mx/wp-content/uploads/downloaded-images/axn/csi-miami-4.webp","start":"16:00","end":"16:50"},{"show":"CSI: Miami","category":"Temporada 1 Episodio 15 - Muerta andante","logo":"https://cdn.programaciontv.com.mx/wp-content/uploads/downloaded-images/axn/csi-miami-5.webp","start":"16:50","end":"17:40"},{"show":"CSI: Miami","category":"Temporada 1 Episodio 16 - Indicios de cosas invisibles","logo":"https://cdn.programaciontv.com.mx/wp-content/uploads/downloaded-images/axn/csi-miami-6.webp","start":"17:40","end":"18:30"},{"show":"NCIS","category":"Temporada 22 Episodio 1 - Nido vacío","logo":"https://cdn.programaciontv.com.mx/wp-content/uploads/downloaded-images/axn/ncis-3.webp","start":"18:30","end":"19:20"},{"show":"NCIS","category":"Temporada 22 Episodio 2 - Cuerpos extraños","logo":"https://cdn.programaciontv.com.mx/wp-content/uploads/downloaded-images/axn/ncis-4.webp","start":"19:20","end":"20:10"},{"show":"NCIS","category":"Temporada 22 Episodio 3 - El problema con Hal","logo":"https://cdn.programaciontv.com.mx/wp-content/uploads/downloaded-images/axn/ncis-5.webp","start":"20:10","end":"21:00"},{"show":"9-1-1","category":"Temporada 4 Episodio 4 - 9-1-1, ¿cuál es su reclamo?","logo":"https://cdn.programaciontv.com.mx/wp-content/uploads/downloaded-images/axn/9-1-1.webp","start":"21:00","end":"21:55"},{"show":"9-1-1","category":"Temporada 4 Episodio 5 - Buck comienza","logo":"https://cdn.programaciontv.com.mx/wp-content/uploads/downloaded-images/axn/9-1-1-1.webp","start":"21:55","end":"22:45"},{"show":"9-1-1","category":"Temporada 4 Episodio 6 - Jinx","logo":"https://cdn.programaciontv.com.mx/wp-content/uploads/downloaded-images/axn/9-1-1-2.webp","start":"22:45","end":"23:35"},{"show":"Criminal Minds","category":"Temporada 8 Episodio 8 - Las ruedas del autobús","logo":"https://cdn.programaciontv.com.mx/wp-content/uploads/downloaded-images/axn/criminal-minds-5.webp","start":"23:35","end":"00:30"}]}