{"channel":"discovery-id","2026-07-16":[{"show":"Misterio en el Hotel Cecil","category":"Temporada 1 Episodio 1 - La muchacha en el tanque de agua","logo":"https://cdn.programaciontv.com.mx/wp-content/uploads/downloaded-images/discovery-id/misterio-en-el-hotel-cecil.webp","start":"22:36","end":"23:27"},{"show":"Misterio en el Hotel Cecil","category":"Temporada 1 Episodio 2 - Habitación 1402","logo":"https://cdn.programaciontv.com.mx/wp-content/uploads/downloaded-images/discovery-id/misterio-en-el-hotel-cecil-1.webp","start":"23:27","end":"00:18"}],"2026-07-17":[{"show":"Misterio en el Hotel Cecil","category":"Temporada 1 Episodio 3 - Desde el noveno piso","logo":"https://cdn.programaciontv.com.mx/wp-content/uploads/downloaded-images/discovery-id/misterio-en-el-hotel-cecil-2.webp","start":"00:18","end":"01:08"},{"show":"Crimen casi perfecto","category":"Temporada 3 Episodio 2 - Horror en Harlem","logo":"https://cdn.programaciontv.com.mx/wp-content/uploads/downloaded-images/discovery-id/crimen-casi-perfecto.webp","start":"01:08","end":"01:58"},{"show":"Jared Fogle: persiguiendo a un monstruo","category":"Temporada 1 Episodio 1 - Parte 1","logo":"https://programaciontv.com.mx/wp-content/uploads/2026/01/pexels-caleboquendo-8254900.webp","start":"01:58","end":"02:47"},{"show":"Jared Fogle: persiguiendo a un monstruo","category":"Temporada 1 Episodio 2 - Parte 2","logo":"https://programaciontv.com.mx/wp-content/uploads/2026/01/pexels-caleboquendo-8254900.webp","start":"02:47","end":"03:35"},{"show":"Jared Fogle: persiguiendo a un monstruo","category":"Temporada 1 Episodio 3 - Parte 3","logo":"https://programaciontv.com.mx/wp-content/uploads/2026/01/pexels-caleboquendo-8254900.webp","start":"03:35","end":"04:24"},{"show":"Feds","category":"Temporada 2 Episodio 3 - Trabajo interno","logo":"https://programaciontv.com.mx/wp-content/uploads/2026/01/pexels-caleboquendo-8254900.webp","start":"04:24","end":"05:12"},{"show":"Feds","category":"Temporada 1 Episodio 3 - Secuestrados","logo":"https://programaciontv.com.mx/wp-content/uploads/2026/01/pexels-caleboquendo-8254900.webp","start":"05:12","end":"06:00"},{"show":"Víctimas del amor","category":"Temporada 4 Episodio 8 - El amor es guerra","logo":"https://cdn.programaciontv.com.mx/wp-content/uploads/downloaded-images/discovery-id/v-ctimas-del-amor.webp","start":"06:00","end":"06:49"},{"show":"Traicionados","category":"Temporada 4 Episodio 9 - El depredador con buena vista","logo":"https://cdn.programaciontv.com.mx/wp-content/uploads/downloaded-images/discovery-id/traicionados.webp","start":"06:49","end":"07:39"},{"show":"Traicionados","category":"Temporada 4 Episodio 7 - Alianzas no sagradas","logo":"https://cdn.programaciontv.com.mx/wp-content/uploads/downloaded-images/discovery-id/traicionados-1.webp","start":"07:39","end":"08:29"},{"show":"La casa del mal","category":"Temporada 8 Episodio 12 - Ella sabía que era un adiós","logo":"https://cdn.programaciontv.com.mx/wp-content/uploads/downloaded-images/discovery-id/la-casa-del-mal.webp","start":"08:29","end":"09:19"},{"show":"Cuando el mal se disfraza","category":"Temporada 1 Episodio 4 - Canta para mí","logo":"https://cdn.programaciontv.com.mx/wp-content/uploads/downloaded-images/discovery-id/cuando-el-mal-se-disfraza.webp","start":"09:19","end":"10:09"},{"show":"Desaparecidos","category":"Temporada 8 Episodio 8 - Sobre el muchacho","logo":"https://cdn.programaciontv.com.mx/wp-content/uploads/downloaded-images/discovery-id/desaparecidos.webp","start":"10:09","end":"10:59"},{"show":"Cintas del crimen","category":"Temporada 8 Episodio 4 - Hice algo realmente malo","logo":"https://cdn.programaciontv.com.mx/wp-content/uploads/downloaded-images/discovery-id/cintas-del-crimen.webp","start":"10:59","end":"11:49"},{"show":"Casados con el mal","category":"Temporada 2 Episodio 2 - Hogar es donde están las pesadillas","logo":"https://programaciontv.com.mx/wp-content/uploads/2026/01/pexels-caleboquendo-8254900.webp","start":"11:49","end":"12:38"},{"show":"Casados con el mal","category":"Temporada 2 Episodio 5 - Fuera de control","logo":"https://programaciontv.com.mx/wp-content/uploads/2026/01/pexels-caleboquendo-8254900.webp","start":"12:38","end":"13:28"},{"show":"Mamá, ¿puedo matar?","category":"Temporada 2 Episodio 5 - Un asunto de familia","logo":"https://programaciontv.com.mx/wp-content/uploads/2026/01/pexels-caleboquendo-8254900.webp","start":"13:28","end":"14:17"},{"show":"Perfecto desconocido","category":"Temporada 1 Episodio 4 - Asesinato en el Día de los Caídos","logo":"https://cdn.programaciontv.com.mx/wp-content/uploads/downloaded-images/discovery-id/perfecto-desconocido.webp","start":"14:17","end":"15:07"},{"show":"Perfecto desconocido","category":"Temporada 1 Episodio 5 - Elige tu veneno","logo":"https://cdn.programaciontv.com.mx/wp-content/uploads/downloaded-images/discovery-id/perfecto-desconocido-1.webp","start":"15:07","end":"15:57"},{"show":"Perfecto desconocido","category":"Temporada 1 Episodio 6 - El teniente de la calle Lampson","logo":"https://cdn.programaciontv.com.mx/wp-content/uploads/downloaded-images/discovery-id/perfecto-desconocido-2.webp","start":"15:57","end":"16:46"},{"show":"Crimen casi perfecto","category":"Temporada 3 Episodio 3 - Muerte al volante","logo":"https://cdn.programaciontv.com.mx/wp-content/uploads/downloaded-images/discovery-id/crimen-casi-perfecto-1.webp","start":"16:46","end":"17:36"},{"show":"Muerte en el pueblo","category":"Temporada 8 Episodio 5 - Algo le pasó","logo":"https://cdn.programaciontv.com.mx/wp-content/uploads/downloaded-images/discovery-id/muerte-en-el-pueblo.webp","start":"17:36","end":"18:26"},{"show":"Traicionados","category":"Temporada 4 Episodio 4 - El beso de la muerte","logo":"https://cdn.programaciontv.com.mx/wp-content/uploads/downloaded-images/discovery-id/traicionados-2.webp","start":"18:26","end":"19:17"},{"show":"Traicionados","category":"Temporada 4 Episodio 1 - Un trago amargo","logo":"https://cdn.programaciontv.com.mx/wp-content/uploads/downloaded-images/discovery-id/traicionados-3.webp","start":"19:17","end":"20:07"},{"show":"Casados con el mal","category":"Temporada 2 Episodio 1 - Dosis letal","logo":"https://programaciontv.com.mx/wp-content/uploads/2026/01/pexels-caleboquendo-8254900.webp","start":"20:07","end":"20:57"},{"show":"Casados con el mal","category":"Temporada 2 Episodio 4 - Lo que hay debajo","logo":"https://programaciontv.com.mx/wp-content/uploads/2026/01/pexels-caleboquendo-8254900.webp","start":"20:57","end":"21:46"},{"show":"Mamá, ¿puedo matar?","category":"Temporada 2 Episodio 6 - Los secretos de un soldado","logo":"https://programaciontv.com.mx/wp-content/uploads/2026/01/pexels-caleboquendo-8254900.webp","start":"21:46","end":"22:36"},{"show":"Viudo Negro: las 6 esposas de Thomas Randolph","category":"Temporada 1 Episodio 1 - Muy suertudo","logo":"https://programaciontv.com.mx/wp-content/uploads/2026/01/pexels-caleboquendo-8254900.webp","start":"22:36","end":"23:27"},{"show":"Viudo Negro: las 6 esposas de Thomas Randolph","category":"Temporada 1 Episodio 2 - Telaraña de esposas","logo":"https://programaciontv.com.mx/wp-content/uploads/2026/01/pexels-caleboquendo-8254900.webp","start":"23:27","end":"00:18"}],"2026-07-18":[{"show":"Viudo Negro: las 6 esposas de Thomas Randolph","category":"Temporada 1 Episodio 3 - Esto es la guerra","logo":"https://programaciontv.com.mx/wp-content/uploads/2026/01/pexels-caleboquendo-8254900.webp","start":"00:18","end":"01:08"},{"show":"Crimen casi perfecto","category":"Temporada 3 Episodio 3 - Muerte al volante","logo":"https://cdn.programaciontv.com.mx/wp-content/uploads/downloaded-images/discovery-id/crimen-casi-perfecto-1.webp","start":"01:08","end":"01:58"},{"show":"Traicionados","category":"Temporada 4 Episodio 4 - El beso de la muerte","logo":"https://cdn.programaciontv.com.mx/wp-content/uploads/downloaded-images/discovery-id/traicionados-2.webp","start":"01:58","end":"02:47"},{"show":"Traicionados","category":"Temporada 4 Episodio 1 - Un trago amargo","logo":"https://cdn.programaciontv.com.mx/wp-content/uploads/downloaded-images/discovery-id/traicionados-3.webp","start":"02:47","end":"03:35"},{"show":"Casados con el mal","category":"Temporada 2 Episodio 1 - Dosis letal","logo":"https://programaciontv.com.mx/wp-content/uploads/2026/01/pexels-caleboquendo-8254900.webp","start":"03:35","end":"04:24"},{"show":"Casados con el mal","category":"Temporada 2 Episodio 4 - Lo que hay debajo","logo":"https://programaciontv.com.mx/wp-content/uploads/2026/01/pexels-caleboquendo-8254900.webp","start":"04:24","end":"05:12"},{"show":"Mamá, ¿puedo matar?","category":"Temporada 2 Episodio 6 - Los secretos de un soldado","logo":"https://programaciontv.com.mx/wp-content/uploads/2026/01/pexels-caleboquendo-8254900.webp","start":"05:12","end":"06:00"},{"show":"Víctimas del amor","category":"Temporada 4 Episodio 3 - Sé mi salvador","logo":"https://cdn.programaciontv.com.mx/wp-content/uploads/downloaded-images/discovery-id/v-ctimas-del-amor-1.webp","start":"06:00","end":"06:49"},{"show":"Cintas del crimen","category":"Temporada 5 Episodio 4 - ¿Qué hay en la mochila?","logo":"https://cdn.programaciontv.com.mx/wp-content/uploads/downloaded-images/discovery-id/cintas-del-crimen-1.webp","start":"06:49","end":"07:39"},{"show":"Cintas del crimen","category":"Temporada 5 Episodio 3 - Huellas en la nieve","logo":"https://cdn.programaciontv.com.mx/wp-content/uploads/downloaded-images/discovery-id/cintas-del-crimen-2.webp","start":"07:39","end":"08:29"},{"show":"La casa del mal","category":"Temporada 8 Episodio 13 - Escondió el cuchillo en la caja de juguetes","logo":"https://cdn.programaciontv.com.mx/wp-content/uploads/downloaded-images/discovery-id/la-casa-del-mal-1.webp","start":"08:29","end":"09:19"},{"show":"Cuando el mal se disfraza","category":"Temporada 1 Episodio 3 - Mi padre, el asesino","logo":"https://cdn.programaciontv.com.mx/wp-content/uploads/downloaded-images/discovery-id/cuando-el-mal-se-disfraza-1.webp","start":"09:19","end":"10:09"},{"show":"Desaparecidos","category":"Temporada 8 Episodio 13 - El largo camino a casa","logo":"https://cdn.programaciontv.com.mx/wp-content/uploads/downloaded-images/discovery-id/desaparecidos-1.webp","start":"10:09","end":"10:59"},{"show":"Demonios de Hollywood","category":"Temporada 2 Episodio 4 - Doctores complacientes","logo":"https://programaciontv.com.mx/wp-content/uploads/2026/01/pexels-caleboquendo-8254900.webp","start":"10:59","end":"12:38"},{"show":"Reinas caídas","category":"Episodio 3 - Belleza al acecho","logo":"https://cdn.programaciontv.com.mx/wp-content/uploads/downloaded-images/discovery-id/reinas-ca-das.webp","start":"12:38","end":"13:28"},{"show":"Reinas caídas","category":"Temporada 1 - Obsesión fatal","logo":"https://cdn.programaciontv.com.mx/wp-content/uploads/downloaded-images/discovery-id/reinas-ca-das-1.webp","start":"13:28","end":"14:17"},{"show":"Investigación en curso","category":"Temporada 7 Episodio 7 - Los niños sufren","logo":"https://programaciontv.com.mx/wp-content/uploads/2026/01/pexels-caleboquendo-8254900.webp","start":"14:17","end":"15:07"},{"show":"Investigación en curso","category":"Temporada 5 Episodio 8 - Secretos en el ADN","logo":"https://cdn.programaciontv.com.mx/wp-content/uploads/downloaded-images/discovery-id/investigaci-n-en-curso.webp","start":"15:07","end":"15:57"},{"show":"Investigación en curso","category":"Temporada 7 Episodio 9 - Enemigos invisibles","logo":"https://programaciontv.com.mx/wp-content/uploads/2026/01/pexels-caleboquendo-8254900.webp","start":"15:57","end":"16:46"},{"show":"Crimen casi perfecto","category":"Temporada 3 Episodio 4 - La última danza","logo":"https://cdn.programaciontv.com.mx/wp-content/uploads/downloaded-images/discovery-id/crimen-casi-perfecto-2.webp","start":"16:46","end":"17:36"},{"show":"Muerte en el pueblo","category":"Temporada 8 Episodio 8 - Amor mortal de verano","logo":"https://cdn.programaciontv.com.mx/wp-content/uploads/downloaded-images/discovery-id/muerte-en-el-pueblo-1.webp","start":"17:36","end":"18:26"},{"show":"El precio de la fama","category":"Temporada 1 Episodio 2 - Hombre de anarquía","logo":"https://programaciontv.com.mx/wp-content/uploads/2026/01/pexels-caleboquendo-8254900.webp","start":"18:26","end":"19:17"},{"show":"Demonios de Hollywood","category":"Temporada 2 Episodio 3 - Marcado por la campana","logo":"https://programaciontv.com.mx/wp-content/uploads/2026/01/pexels-caleboquendo-8254900.webp","start":"19:17","end":"20:57"},{"show":"Reinas caídas","category":"Temporada 1 Episodio 5 - Si las miradas mataran","logo":"https://cdn.programaciontv.com.mx/wp-content/uploads/downloaded-images/discovery-id/reinas-ca-das-2.webp","start":"20:57","end":"21:46"},{"show":"Reinas caídas","category":"Temporada 1 Episodio 6 - Pecados mortales","logo":"https://cdn.programaciontv.com.mx/wp-content/uploads/downloaded-images/discovery-id/reinas-ca-das-3.webp","start":"21:46","end":"22:36"},{"show":"El misterioso asesinato de Susan Powell","category":"Temporada 1 Episodio 1 - Parte 1","logo":"https://cdn.programaciontv.com.mx/wp-content/uploads/downloaded-images/discovery-id/el-misterioso-asesinato-de-susan-powell.webp","start":"22:36","end":"23:27"},{"show":"El misterioso asesinato de Susan Powell","category":"Temporada 1 Episodio 2 - Parte 2","logo":"https://cdn.programaciontv.com.mx/wp-content/uploads/downloaded-images/discovery-id/el-misterioso-asesinato-de-susan-powell-1.webp","start":"23:27","end":"00:18"}]}