{"channel":"entertainment","2026-06-27":[{"show":"Botched Presents: Plastic Surgery Rewind","category":"Temporada 1 Episodio 5 - Caminos separados","logo":"https://programaciontv.com.mx/wp-content/uploads/2026/01/pexels-caleboquendo-8254900.webp","start":"22:25","end":"23:15"},{"show":"Love Island","category":"Temporada 6 Episodio 34","logo":"https://programaciontv.com.mx/wp-content/uploads/2026/01/pexels-caleboquendo-8254900.webp","start":"23:15","end":"00:20"}],"2026-06-28":[{"show":"Love Island","category":"Temporada 6 Episodio 35 - Aftersun #6.35","logo":"https://programaciontv.com.mx/wp-content/uploads/2026/01/pexels-caleboquendo-8254900.webp","start":"00:20","end":"01:20"},{"show":"Love Island","category":"Temporada 6 Episodio 36","logo":"https://programaciontv.com.mx/wp-content/uploads/2026/01/pexels-caleboquendo-8254900.webp","start":"01:20","end":"03:25"},{"show":"Love Island","category":"Temporada 6 Episodio 37 - Reencuentro","logo":"https://programaciontv.com.mx/wp-content/uploads/2026/01/pexels-caleboquendo-8254900.webp","start":"03:25","end":"04:50"},{"show":"Love Island","category":"Temporada 4 Episodio 1","logo":"https://programaciontv.com.mx/wp-content/uploads/2026/01/pexels-caleboquendo-8254900.webp","start":"04:50","end":"06:00"},{"show":"Vanderpump Rules","category":"Temporada 3 Episodio 17 - Jax se quiebra","logo":"https://programaciontv.com.mx/wp-content/uploads/2026/01/pexels-caleboquendo-8254900.webp","start":"06:00","end":"06:50"},{"show":"Vanderpump Rules","category":"Temporada 3 Episodio 18 - Destronado","logo":"https://programaciontv.com.mx/wp-content/uploads/2026/01/pexels-caleboquendo-8254900.webp","start":"06:50","end":"07:40"},{"show":"Vanderpump Rules","category":"Temporada 3 Episodio 19 - Reunión - Parte I","logo":"https://programaciontv.com.mx/wp-content/uploads/2026/01/pexels-caleboquendo-8254900.webp","start":"07:40","end":"08:30"},{"show":"Vanderpump Rules","category":"Temporada 11 Episodio 17 - Reunión - Parte 2","logo":"https://programaciontv.com.mx/wp-content/uploads/2026/01/pexels-caleboquendo-8254900.webp","start":"08:30","end":"09:20"},{"show":"Vanderpump Rules","category":"Temporada 4 Episodio 1 - Se acabó el tiempo de juegos","logo":"https://programaciontv.com.mx/wp-content/uploads/2026/01/pexels-caleboquendo-8254900.webp","start":"09:20","end":"10:10"},{"show":"Vanderpump Rules","category":"Temporada 4 Episodio 2 - Sangre nueva","logo":"https://programaciontv.com.mx/wp-content/uploads/2026/01/pexels-caleboquendo-8254900.webp","start":"10:10","end":"11:00"},{"show":"Vanderpump Rules","category":"Temporada 4 Episodio 3 - Pequeñas mentiras bonitas","logo":"https://programaciontv.com.mx/wp-content/uploads/2026/01/pexels-caleboquendo-8254900.webp","start":"11:00","end":"11:50"},{"show":"Las Kardashian","category":"Temporada 14 Episodio 19 - Problemas de trimestre","logo":"https://cdn.programaciontv.com.mx/wp-content/uploads/downloaded-images/entertainment/las-kardashian.webp","start":"11:50","end":"12:40"},{"show":"Las Kardashian","category":"Temporada 14 Episodio 20 - ¿Niño o niña?","logo":"https://cdn.programaciontv.com.mx/wp-content/uploads/downloaded-images/entertainment/las-kardashian-1.webp","start":"12:40","end":"13:30"},{"show":"Las Kardashian","category":"Temporada 14 Episodio 10 - Un día de fiesta muy Kardashian","logo":"https://cdn.programaciontv.com.mx/wp-content/uploads/downloaded-images/entertainment/las-kardashian-2.webp","start":"13:30","end":"14:20"},{"show":"Las Kardashian","category":"Temporada 14 Episodio 1 - Especial de 10º aniversário","logo":"https://cdn.programaciontv.com.mx/wp-content/uploads/downloaded-images/entertainment/las-kardashian-3.webp","start":"14:20","end":"15:30"},{"show":"Las Kardashian","category":"Temporada 15 Episodio 1 - Fotodisputa","logo":"https://cdn.programaciontv.com.mx/wp-content/uploads/downloaded-images/entertainment/las-kardashian-4.webp","start":"15:30","end":"16:20"},{"show":"Las Kardashian","category":"Temporada 15 Episodio 2 - El arte de las bromas","logo":"https://cdn.programaciontv.com.mx/wp-content/uploads/downloaded-images/entertainment/las-kardashian-5.webp","start":"16:20","end":"17:10"},{"show":"Las Kardashian","category":"Temporada 15 Episodio 3 - Hermosísima","logo":"https://cdn.programaciontv.com.mx/wp-content/uploads/downloaded-images/entertainment/las-kardashian-6.webp","start":"17:10","end":"18:00"},{"show":"Las Kardashian","category":"Temporada 15 Episodio 4 - Pesadilla antes de Navidad","logo":"https://cdn.programaciontv.com.mx/wp-content/uploads/downloaded-images/entertainment/las-kardashian-7.webp","start":"18:00","end":"18:50"},{"show":"Botched Presents: Plastic Surgery Rewind","category":"Temporada 1 Episodio 6 - Cada cicatriz tiene su historia","logo":"https://programaciontv.com.mx/wp-content/uploads/2026/01/pexels-caleboquendo-8254900.webp","start":"18:50","end":"19:40"},{"show":"Botched Presents: Plastic Surgery Rewind","category":"Temporada 1 Episodio 7 - Sale el Sol, sale el short","logo":"https://programaciontv.com.mx/wp-content/uploads/2026/01/pexels-caleboquendo-8254900.webp","start":"19:40","end":"20:30"},{"show":"Botched Presents: Plastic Surgery Rewind","category":"Temporada 1 Episodio 8 - Tiempo de sanar","logo":"https://programaciontv.com.mx/wp-content/uploads/2026/01/pexels-caleboquendo-8254900.webp","start":"20:30","end":"21:20"},{"show":"Botched","category":"Temporada 1 Episodio 1 - Muñecas humanas","logo":"https://cdn.programaciontv.com.mx/wp-content/uploads/downloaded-images/entertainment/botched.webp","start":"21:20","end":"22:10"},{"show":"Botched","category":"Temporada 1 Episodio 2 - Janice Dickinson se lo toma muy a pecho","logo":"https://cdn.programaciontv.com.mx/wp-content/uploads/downloaded-images/entertainment/botched-1.webp","start":"22:10","end":"23:00"},{"show":"Love Island","category":"Temporada 4 Episodio 2","logo":"https://programaciontv.com.mx/wp-content/uploads/2026/01/pexels-caleboquendo-8254900.webp","start":"23:00","end":"23:55"},{"show":"Love Island","category":"Temporada 4 Episodio 3","logo":"https://programaciontv.com.mx/wp-content/uploads/2026/01/pexels-caleboquendo-8254900.webp","start":"23:55","end":"00:45"}],"2026-06-29":[{"show":"Love Island","category":"Temporada 4 Episodio 4","logo":"https://programaciontv.com.mx/wp-content/uploads/2026/01/pexels-caleboquendo-8254900.webp","start":"00:45","end":"01:35"},{"show":"Love Island","category":"Temporada 4 Episodio 5","logo":"https://programaciontv.com.mx/wp-content/uploads/2026/01/pexels-caleboquendo-8254900.webp","start":"01:35","end":"02:25"},{"show":"Love Island","category":"Temporada 4 Episodio 6","logo":"https://programaciontv.com.mx/wp-content/uploads/2026/01/pexels-caleboquendo-8254900.webp","start":"02:25","end":"03:15"},{"show":"Te vendo tu mansión: Los Ángeles","category":"Temporada 13 Episodio 3 - ¿Te alegra que sea una captación compartida?","logo":"https://programaciontv.com.mx/wp-content/uploads/2026/01/pexels-caleboquendo-8254900.webp","start":"03:15","end":"04:15"},{"show":"Las Kardashian","category":"Temporada 15 Episodio 5 - La disputa familiar","logo":"https://cdn.programaciontv.com.mx/wp-content/uploads/downloaded-images/entertainment/las-kardashian-8.webp","start":"04:15","end":"05:05"},{"show":"Las Kardashian","category":"Temporada 15 Episodio 6 - Amamos Chicago","logo":"https://cdn.programaciontv.com.mx/wp-content/uploads/downloaded-images/entertainment/las-kardashian-9.webp","start":"05:05","end":"06:00"},{"show":"Las Kardashian","category":"Temporada 15 Episodio 7 - La tormenta perfecta","logo":"https://cdn.programaciontv.com.mx/wp-content/uploads/downloaded-images/entertainment/las-kardashian-10.webp","start":"06:00","end":"07:00"},{"show":"Project Runway","category":"Temporada 18 Episodio 8 - Puro genio","logo":"https://cdn.programaciontv.com.mx/wp-content/uploads/downloaded-images/entertainment/project-runway.webp","start":"07:00","end":"08:00"},{"show":"Project Runway","category":"Temporada 18 Episodio 9 - ¡A trajearse!","logo":"https://cdn.programaciontv.com.mx/wp-content/uploads/downloaded-images/entertainment/project-runway-1.webp","start":"08:00","end":"09:00"},{"show":"Vanderpump Rules","category":"Temporada 4 Episodio 5 - Gallo del corral","logo":"https://programaciontv.com.mx/wp-content/uploads/2026/01/pexels-caleboquendo-8254900.webp","start":"09:00","end":"09:50"},{"show":"Vanderpump Rules","category":"Temporada 4 Episodio 6 - Chupetones","logo":"https://programaciontv.com.mx/wp-content/uploads/2026/01/pexels-caleboquendo-8254900.webp","start":"09:50","end":"10:40"},{"show":"Vanderpump Rules","category":"Temporada 4 Episodio 7 - Escupir tomar","logo":"https://programaciontv.com.mx/wp-content/uploads/2026/01/pexels-caleboquendo-8254900.webp","start":"10:40","end":"11:30"},{"show":"Las Kardashian","category":"Temporada 15 Episodio 8 - Una modelo americana en París","logo":"https://cdn.programaciontv.com.mx/wp-content/uploads/downloaded-images/entertainment/las-kardashian-11.webp","start":"11:30","end":"12:20"},{"show":"Las Kardashian","category":"Temporada 15 Episodio 9 - Las Kardashian toman Japón","logo":"https://cdn.programaciontv.com.mx/wp-content/uploads/downloaded-images/entertainment/las-kardashian-12.webp","start":"12:20","end":"13:10"},{"show":"Las Kardashian","category":"Temporada 15 Episodio 10 - ¡Vamos a jugar pelota!","logo":"https://cdn.programaciontv.com.mx/wp-content/uploads/downloaded-images/entertainment/las-kardashian-13.webp","start":"13:10","end":"14:00"},{"show":"Project Runway","category":"Temporada 18 Episodio 8 - Puro genio","logo":"https://cdn.programaciontv.com.mx/wp-content/uploads/downloaded-images/entertainment/project-runway.webp","start":"14:00","end":"14:55"},{"show":"Project Runway","category":"Temporada 18 Episodio 9 - ¡A trajearse!","logo":"https://cdn.programaciontv.com.mx/wp-content/uploads/downloaded-images/entertainment/project-runway-1.webp","start":"14:55","end":"15:50"},{"show":"Te vendo tu mansión: Los Ángeles","category":"Temporada 13 Episodio 5 - La casa que construyó Thighmaster","logo":"https://programaciontv.com.mx/wp-content/uploads/2026/01/pexels-caleboquendo-8254900.webp","start":"15:50","end":"16:50"},{"show":"Te vendo tu mansión: Los Ángeles","category":"Temporada 13 Episodio 6 - Dos son compañía, tres son multitud","logo":"https://programaciontv.com.mx/wp-content/uploads/2026/01/pexels-caleboquendo-8254900.webp","start":"16:50","end":"17:50"},{"show":"Love Island","category":"Temporada 4 Episodio 5","logo":"https://programaciontv.com.mx/wp-content/uploads/2026/01/pexels-caleboquendo-8254900.webp","start":"17:50","end":"18:40"},{"show":"Love Island","category":"Temporada 4 Episodio 6","logo":"https://programaciontv.com.mx/wp-content/uploads/2026/01/pexels-caleboquendo-8254900.webp","start":"18:40","end":"19:30"},{"show":"Botched","category":"Temporada 1 Episodio 4 - Remodelando a un \"Believer\"","logo":"https://cdn.programaciontv.com.mx/wp-content/uploads/downloaded-images/entertainment/botched-2.webp","start":"19:30","end":"20:20"},{"show":"Botched","category":"Temporada 1 Episodio 5 - En la camilla con Madonna","logo":"https://cdn.programaciontv.com.mx/wp-content/uploads/downloaded-images/entertainment/botched-3.webp","start":"20:20","end":"21:10"},{"show":"Botched","category":"Temporada 1 Episodio 6 - Pechoadicta","logo":"https://cdn.programaciontv.com.mx/wp-content/uploads/downloaded-images/entertainment/botched-4.webp","start":"21:10","end":"22:00"},{"show":"Love Island","category":"Temporada 4 Episodio 7","logo":"https://programaciontv.com.mx/wp-content/uploads/2026/01/pexels-caleboquendo-8254900.webp","start":"22:00","end":"22:50"},{"show":"Love Island","category":"Temporada 4 Episodio 8","logo":"https://programaciontv.com.mx/wp-content/uploads/2026/01/pexels-caleboquendo-8254900.webp","start":"22:50","end":"23:40"},{"show":"Te vendo tu mansión: Los Ángeles","category":"Temporada 13 Episodio 5 - La casa que construyó Thighmaster","logo":"https://programaciontv.com.mx/wp-content/uploads/2026/01/pexels-caleboquendo-8254900.webp","start":"23:40","end":"00:40"}]}